finmetrics/__init__.py
finmetrics/main.py
finmetrics-0.1.3.dist-info/METADATA
finmetrics-0.1.3.dist-info/WHEEL
finmetrics-0.1.3.dist-info/top_level.txt
finmetrics-0.1.3.dist-info/RECORD
