Metadata-Version: 2.1
Name: finmetrics
Version: 0.1.3
Summary: A python package to perform financial operations
Home-page: https://github.com/MihirGajjar27/finmetrics
Author: Mihir Gajjar
Classifier: Programming Language :: Python :: 3
Classifier: License :: OSI Approved :: MIT License
Classifier: Operating System :: OS Independent
Requires-Python: >=3.9.6
